autoFillMaskWithCandi/__init__.py
autoFillMaskWithCandi/autoFillMaskWithCandi.py
autoFillMaskWithCandi-0.0.3.dist-info/LICENSE.txt
autoFillMaskWithCandi-0.0.3.dist-info/METADATA
autoFillMaskWithCandi-0.0.3.dist-info/WHEEL
autoFillMaskWithCandi-0.0.3.dist-info/top_level.txt
autoFillMaskWithCandi-0.0.3.dist-info/RECORD
